LICENSE
MANIFEST.in
README.md
setup.py
django_secup.egg-info/PKG-INFO
django_secup.egg-info/SOURCES.txt
django_secup.egg-info/dependency_links.txt
django_secup.egg-info/top_level.txt
secup/__init__.py
secup/admin.py
secup/apps.py
secup/forms.py
secup/models.py
secup/settings.py
secup/tests.py
secup/urls.py
secup/utils.py
secup/views.py
secup/migrations/0001_initial.py
secup/migrations/__init__.py
secup/templates/secup/base.html
secup/templates/secup/email_invited.html
secup/templates/secup/email_invited.txt
secup/templates/secup/email_managers.html
secup/templates/secup/email_managers.txt
secup/templates/secup/email_uploaded.html
secup/templates/secup/email_uploaded.txt
secup/templates/secup/files.html
secup/templates/secup/invite.html
secup/templates/secup/thanks.html
secup/templates/secup/upload.html
secup/templates/secup/upload_to_secup.html